{
  "global_score": 5.4,
  "short_summary": "NATO summit, Typhoon Bavi hits Guam, Canada submarine deal",
  "rationale": "US faces direct military implications from NATO summit outcomes on Ukraine aid and Russia escalation; Typhoon Bavi threatens US territory in Guam; Canada submarine procurement affects North American defence posture.",
  "top_events": [
    {
      "title": "Typhoon Bavi — Guam landfall confirmed",
      "summary": "Super Typhoon Bavi makes direct landfall on Guam, a critical US military hub in the Pacific; threatens US military infrastructure, personnel, and regional strategic position.",
      "score": 5.4,
      "sentiment": "negative",
      "nowosc": "nowe",
      "category": "katastrofa",
      "sources": [
        "stan_swiata"
      ],
      "source_links": []
    },
    {
      "title": "NATO summit — Ukraine aid and strategy",
      "summary": "High-stakes NATO summit determines US military commitments to Ukraine and European defence; outcomes directly affect US military spending, troop deployments, and strategic priorities.",
      "score": 3.5,
      "sentiment": "neutral",
      "nowosc": "kontynuacja",
      "category": "geopolityka",
      "sources": [
        "BBC"
      ],
      "source_links": [
        {
          "name": "BBC",
          "url": "https://www.bbc.co.uk/news/articles/c9d227e5zj6o?at_medium=RSS&at_campaign=rss"
        }
      ]
    },
    {
      "title": "Canada to buy 12 hi-tech German submarines after bidding war",
      "summary": "Canada's C$150bn German submarine procurement strengthens North American defence posture; affects US-Canada military interoperability and Arctic security strategy.",
      "score": 3.6,
      "sentiment": "positive",
      "nowosc": "nowe",
      "category": "geopolityka",
      "sources": [
        "Guardian"
      ],
      "source_links": [
        {
          "name": "Guardian",
          "url": "https://www.theguardian.com/world/2026/jul/06/canada-buys-12-tkms-german-norwegian-submarines-after-bidding-war"
        }
      ]
    }
  ],
  "level_label": "Elevated",
  "trend": "stable",
  "lens_id": "us",
  "lens_name_en": "United States",
  "updated_at": "2026-07-07T04:01:57.217786Z",
  "liczba_naglowkow": 30,
  "tone": "negative",
  "events_anchor_at": "2026-07-07T04:01:57.217786Z",
  "score_history": [
    {
      "t": "2026-07-05T04:01:59.853859Z",
      "s": 2.2
    },
    {
      "t": "2026-07-05T05:02:22.629210Z",
      "s": 2.3
    },
    {
      "t": "2026-07-05T06:02:50.987092Z",
      "s": 2.2
    },
    {
      "t": "2026-07-05T07:01:54.652790Z",
      "s": 2.0
    },
    {
      "t": "2026-07-05T08:01:55.947945Z",
      "s": 2.0
    },
    {
      "t": "2026-07-05T09:02:03.850023Z",
      "s": 3.0
    },
    {
      "t": "2026-07-05T09:48:49.343247Z",
      "s": 2.4
    },
    {
      "t": "2026-07-05T10:01:59.945882Z",
      "s": 2.5
    },
    {
      "t": "2026-07-05T11:02:51.626336Z",
      "s": 2.5
    },
    {
      "t": "2026-07-05T12:02:09.430199Z",
      "s": 2.4
    },
    {
      "t": "2026-07-05T13:02:00.331706Z",
      "s": 2.6
    },
    {
      "t": "2026-07-05T14:02:01.185697Z",
      "s": 3.2
    },
    {
      "t": "2026-07-05T15:02:02.654208Z",
      "s": 3.1
    },
    {
      "t": "2026-07-05T16:02:06.787285Z",
      "s": 3.2
    },
    {
      "t": "2026-07-05T17:02:02.461374Z",
      "s": 3.1
    },
    {
      "t": "2026-07-05T18:02:08.300456Z",
      "s": 3.0
    },
    {
      "t": "2026-07-05T18:52:23.009743Z",
      "s": 3.0
    },
    {
      "t": "2026-07-05T19:02:07.320699Z",
      "s": 3.0
    },
    {
      "t": "2026-07-05T20:02:11.763954Z",
      "s": 3.0
    },
    {
      "t": "2026-07-05T21:02:11.722608Z",
      "s": 3.4
    },
    {
      "t": "2026-07-05T22:02:12.565662Z",
      "s": 3.2
    },
    {
      "t": "2026-07-05T22:39:01.513056Z",
      "s": 4.5
    },
    {
      "t": "2026-07-05T23:02:11.655627Z",
      "s": 4.3
    },
    {
      "t": "2026-07-06T00:02:04.361021Z",
      "s": 3.9
    },
    {
      "t": "2026-07-06T01:02:32.862839Z",
      "s": 3.6
    },
    {
      "t": "2026-07-06T02:01:55.563090Z",
      "s": 3.2
    },
    {
      "t": "2026-07-06T03:01:58.487987Z",
      "s": 3.1
    },
    {
      "t": "2026-07-06T04:02:08.006647Z",
      "s": 3.2
    },
    {
      "t": "2026-07-06T04:37:14.334284Z",
      "s": 3.4
    },
    {
      "t": "2026-07-06T05:02:10.007467Z",
      "s": 3.4
    },
    {
      "t": "2026-07-06T06:02:00.421706Z",
      "s": 4.8
    },
    {
      "t": "2026-07-06T07:01:58.692810Z",
      "s": 5.1
    },
    {
      "t": "2026-07-06T08:02:29.907742Z",
      "s": 5.3
    },
    {
      "t": "2026-07-06T09:02:02.090105Z",
      "s": 5.4
    },
    {
      "t": "2026-07-06T10:02:00.564723Z",
      "s": 5.4
    },
    {
      "t": "2026-07-06T11:02:00.619801Z",
      "s": 5.4
    },
    {
      "t": "2026-07-06T12:02:53.813026Z",
      "s": 5.4
    },
    {
      "t": "2026-07-06T13:01:54.396500Z",
      "s": 5.4
    },
    {
      "t": "2026-07-06T13:06:00.892812Z",
      "s": 5.4
    },
    {
      "t": "2026-07-06T14:03:27.426325Z",
      "s": 5.4
    },
    {
      "t": "2026-07-06T15:01:56.307849Z",
      "s": 5.4
    },
    {
      "t": "2026-07-06T16:01:57.916000Z",
      "s": 5.4
    },
    {
      "t": "2026-07-06T17:01:59.037019Z",
      "s": 5.4
    },
    {
      "t": "2026-07-06T18:01:53.364138Z",
      "s": 5.4
    },
    {
      "t": "2026-07-06T19:01:51.758668Z",
      "s": 5.4
    },
    {
      "t": "2026-07-06T19:24:04.639053Z",
      "s": 5.4
    },
    {
      "t": "2026-07-06T20:01:50.327998Z",
      "s": 5.4
    },
    {
      "t": "2026-07-06T21:01:56.718773Z",
      "s": 5.4
    },
    {
      "t": "2026-07-06T22:01:55.991946Z",
      "s": 5.4
    },
    {
      "t": "2026-07-06T23:01:55.019189Z",
      "s": 5.4
    },
    {
      "t": "2026-07-06T23:52:56.913844Z",
      "s": 5.4
    },
    {
      "t": "2026-07-07T00:01:52.343857Z",
      "s": 5.4
    },
    {
      "t": "2026-07-07T01:02:01.768814Z",
      "s": 5.4
    },
    {
      "t": "2026-07-07T02:01:52.008667Z",
      "s": 5.4
    },
    {
      "t": "2026-07-07T03:01:58.420018Z",
      "s": 5.4
    },
    {
      "t": "2026-07-07T04:01:57.217786Z",
      "s": 5.4
    }
  ]
}