{
  "global_score": 1.1,
  "short_summary": "France confirms first Ebola case",
  "rationale": "No headline this cycle has a direct or meaningful impact on daily life in Portugal; the France Ebola case remains the closest relevant item but shows no spread.",
  "top_events": [
    {
      "title": "France confirms first Ebola case in doctor returning from DR Congo",
      "summary": "A single Ebola case confirmed in neighboring France; no spread reported and no travel alerts issued. Portugal monitors but no direct impact yet.",
      "score": 1.2,
      "sentiment": "negative",
      "nowosc": "kontynuacja",
      "category": "katastrofa",
      "sources": [
        "BBC",
        "Al Jazeera"
      ]
    },
    {
      "title": "Power outages hit France as record heatwave set to peak",
      "summary": "Record heatwave causing power outages in France; Iberian Peninsula may face similar heat stress but no Portugal-specific emergency reported.",
      "score": 1.2,
      "sentiment": "negative",
      "nowosc": "kontynuacja",
      "category": "katastrofa",
      "sources": [
        "BBC"
      ]
    },
    {
      "title": "Dozens of ships head through Strait of Hormuz after US-Iran deal",
      "summary": "Hormuz shipping resuming normally — a mild positive signal for global energy prices that could slightly ease fuel costs in Portugal.",
      "score": 1.0,
      "sentiment": "positive",
      "nowosc": "kontynuacja",
      "category": "gospodarka",
      "sources": [
        "BBC"
      ]
    }
  ],
  "level_label": "Stable",
  "trend": "stable",
  "lens_id": "pt",
  "lens_name_en": "Portugal",
  "updated_at": "2026-06-24T12:02:31.442095Z",
  "liczba_naglowkow": 45,
  "tone": "neutral",
  "events_anchor_at": "2026-06-24T10:02:35.128804Z",
  "score_history": [
    {
      "t": "2026-06-22T13:02:07.627607Z",
      "s": 1.8
    },
    {
      "t": "2026-06-22T14:02:14.131704Z",
      "s": 1.4
    },
    {
      "t": "2026-06-22T15:02:11.034333Z",
      "s": 1.0
    },
    {
      "t": "2026-06-22T16:02:14.993402Z",
      "s": 1.0
    },
    {
      "t": "2026-06-22T16:16:59.982449Z",
      "s": 1.5
    },
    {
      "t": "2026-06-22T17:02:21.867498Z",
      "s": 1.2
    },
    {
      "t": "2026-06-22T18:02:23.012104Z",
      "s": 1.0
    },
    {
      "t": "2026-06-22T19:02:16.829539Z",
      "s": 1.5
    },
    {
      "t": "2026-06-22T20:02:14.547239Z",
      "s": 1.2
    },
    {
      "t": "2026-06-22T21:02:08.679858Z",
      "s": 1.0
    },
    {
      "t": "2026-06-22T22:02:20.577274Z",
      "s": 1.0
    },
    {
      "t": "2026-06-22T22:27:53.940103Z",
      "s": 1.0
    },
    {
      "t": "2026-06-22T23:02:12.914502Z",
      "s": 1.5
    },
    {
      "t": "2026-06-23T00:02:22.994356Z",
      "s": 3.0
    },
    {
      "t": "2026-06-23T01:02:09.088733Z",
      "s": 2.7
    },
    {
      "t": "2026-06-23T02:02:04.715146Z",
      "s": 2.4
    },
    {
      "t": "2026-06-23T03:02:07.751397Z",
      "s": 2.1
    },
    {
      "t": "2026-06-23T04:02:09.543889Z",
      "s": 1.8
    },
    {
      "t": "2026-06-23T05:02:21.284803Z",
      "s": 1.5
    },
    {
      "t": "2026-06-23T06:02:11.330996Z",
      "s": 1.2
    },
    {
      "t": "2026-06-23T07:02:23.079231Z",
      "s": 1.0
    },
    {
      "t": "2026-06-23T08:02:16.250027Z",
      "s": 1.0
    },
    {
      "t": "2026-06-23T09:02:24.336248Z",
      "s": 1.0
    },
    {
      "t": "2026-06-23T10:02:23.955027Z",
      "s": 1.0
    },
    {
      "t": "2026-06-23T10:51:39.497766Z",
      "s": 1.0
    },
    {
      "t": "2026-06-23T11:02:24.025983Z",
      "s": 1.0
    },
    {
      "t": "2026-06-23T12:02:29.499677Z",
      "s": 1.0
    },
    {
      "t": "2026-06-23T13:02:24.064063Z",
      "s": 1.0
    },
    {
      "t": "2026-06-23T14:02:23.141174Z",
      "s": 1.0
    },
    {
      "t": "2026-06-23T15:02:34.738622Z",
      "s": 1.0
    },
    {
      "t": "2026-06-23T16:02:32.820513Z",
      "s": 1.0
    },
    {
      "t": "2026-06-23T17:02:37.431970Z",
      "s": 1.0
    },
    {
      "t": "2026-06-23T18:02:30.105108Z",
      "s": 1.0
    },
    {
      "t": "2026-06-23T18:20:27.810691Z",
      "s": 1.0
    },
    {
      "t": "2026-06-23T19:02:24.466093Z",
      "s": 1.0
    },
    {
      "t": "2026-06-23T20:02:40.481290Z",
      "s": 1.0
    },
    {
      "t": "2026-06-23T21:02:35.076340Z",
      "s": 1.0
    },
    {
      "t": "2026-06-23T22:02:30.581704Z",
      "s": 1.0
    },
    {
      "t": "2026-06-23T23:02:27.704364Z",
      "s": 1.0
    },
    {
      "t": "2026-06-23T23:34:03.620142Z",
      "s": 1.0
    },
    {
      "t": "2026-06-24T00:02:24.854554Z",
      "s": 1.0
    },
    {
      "t": "2026-06-24T01:02:16.352629Z",
      "s": 1.0
    },
    {
      "t": "2026-06-24T02:02:22.259140Z",
      "s": 2.0
    },
    {
      "t": "2026-06-24T03:02:19.755869Z",
      "s": 1.7
    },
    {
      "t": "2026-06-24T04:02:16.232792Z",
      "s": 1.2
    },
    {
      "t": "2026-06-24T05:02:28.311114Z",
      "s": 2.5
    },
    {
      "t": "2026-06-24T06:02:27.287419Z",
      "s": 1.7
    },
    {
      "t": "2026-06-24T07:02:22.570603Z",
      "s": 1.2
    },
    {
      "t": "2026-06-24T08:02:34.226709Z",
      "s": 2.0
    },
    {
      "t": "2026-06-24T09:02:27.898777Z",
      "s": 1.5
    },
    {
      "t": "2026-06-24T10:02:35.128804Z",
      "s": 2.5
    },
    {
      "t": "2026-06-24T11:02:33.016524Z",
      "s": 2.0
    },
    {
      "t": "2026-06-24T11:24:25.637660Z",
      "s": 1.5
    },
    {
      "t": "2026-06-24T12:02:31.442095Z",
      "s": 1.1
    }
  ]
}