{
  "global_score": 2.3,
  "short_summary": "Heatwave reaching Poland, 40°C forecast",
  "rationale": "The heatwave reaching 40°C in Poland and Germany is the most directly relevant event for a Polish resident this cycle, but it is a continuation of the already-tracked situation; no new qualitative escalation across any tracked topic.",
  "top_events": [
    {
      "title": "Weather tracker: Heatwave expected to bring Germany and Poland to 40C",
      "summary": "Extreme heat directly affects daily life in Poland with 40°C forecast, but this is a continuation of the already-tracked heatwave — no new qualitative escalation beyond what was known.",
      "score": 2.3,
      "sentiment": "negative",
      "nowosc": "kontynuacja",
      "category": "katastrofa",
      "sources": [
        "Guardian"
      ]
    },
    {
      "title": "Trump accuses Iran of ceasefire breach after Strait of Hormuz attack",
      "summary": "Rhetoric from Trump about Iran and the Strait of Hormuz; no confirmed new military action that would affect Polish energy prices or security. Continuation of background tension.",
      "score": 2.0,
      "sentiment": "neutral",
      "nowosc": "kontynuacja",
      "category": "geopolityka",
      "sources": [
        "BBC"
      ]
    },
    {
      "title": "Venezuela quake death toll reaches 920",
      "summary": "Death toll rising sharply in Venezuela but this has no direct link to Poland's daily life or economy.",
      "score": 1.5,
      "sentiment": "negative",
      "nowosc": "kontynuacja",
      "category": "katastrofa",
      "sources": [
        "Guardian"
      ]
    }
  ],
  "ostatnia_ocena": 2.4,
  "level_label": "Stable",
  "trend": "stable",
  "lens_id": "pl",
  "lens_name_en": "Poland",
  "updated_at": "2026-06-26T18:16:30.846246Z",
  "liczba_naglowkow": 45,
  "tone": "negative",
  "events_anchor_at": "2026-06-26T08:36:57.255686Z",
  "score_history": [
    {
      "t": "2026-06-24T18:23:59.285248Z",
      "s": 1.0
    },
    {
      "t": "2026-06-24T19:02:29.443153Z",
      "s": 1.0
    },
    {
      "t": "2026-06-24T20:02:31.189443Z",
      "s": 1.0
    },
    {
      "t": "2026-06-24T21:02:33.383135Z",
      "s": 1.0
    },
    {
      "t": "2026-06-24T22:02:27.828878Z",
      "s": 1.0
    },
    {
      "t": "2026-06-24T23:02:18.387884Z",
      "s": 1.0
    },
    {
      "t": "2026-06-24T23:46:12.864081Z",
      "s": 1.0
    },
    {
      "t": "2026-06-25T00:02:26.881752Z",
      "s": 1.0
    },
    {
      "t": "2026-06-25T01:02:21.386616Z",
      "s": 1.0
    },
    {
      "t": "2026-06-25T02:02:33.883292Z",
      "s": 1.5
    },
    {
      "t": "2026-06-25T03:02:27.100253Z",
      "s": 1.2
    },
    {
      "t": "2026-06-25T04:02:27.362221Z",
      "s": 1.0
    },
    {
      "t": "2026-06-25T05:02:34.594454Z",
      "s": 1.0
    },
    {
      "t": "2026-06-25T06:02:27.160357Z",
      "s": 1.0
    },
    {
      "t": "2026-06-25T07:02:33.717763Z",
      "s": 1.0
    },
    {
      "t": "2026-06-25T08:02:41.483856Z",
      "s": 1.0
    },
    {
      "t": "2026-06-25T09:02:36.807283Z",
      "s": 1.0
    },
    {
      "t": "2026-06-25T10:02:32.620487Z",
      "s": 1.0
    },
    {
      "t": "2026-06-25T10:31:37.575488Z",
      "s": 1.0
    },
    {
      "t": "2026-06-25T11:02:26.521584Z",
      "s": 1.0
    },
    {
      "t": "2026-06-25T12:02:27.865634Z",
      "s": 1.0
    },
    {
      "t": "2026-06-25T13:02:36.481675Z",
      "s": 1.0
    },
    {
      "t": "2026-06-25T14:02:35.289569Z",
      "s": 1.0
    },
    {
      "t": "2026-06-25T15:02:34.202759Z",
      "s": 1.0
    },
    {
      "t": "2026-06-25T15:57:37.651906Z",
      "s": 2.0
    },
    {
      "t": "2026-06-25T16:02:30.122252Z",
      "s": 2.0
    },
    {
      "t": "2026-06-25T17:02:25.305089Z",
      "s": 2.0
    },
    {
      "t": "2026-06-25T18:02:39.098590Z",
      "s": 2.0
    },
    {
      "t": "2026-06-25T18:38:33.099278Z",
      "s": 2.0
    },
    {
      "t": "2026-06-25T19:02:34.807298Z",
      "s": 2.0
    },
    {
      "t": "2026-06-25T20:02:36.497170Z",
      "s": 2.0
    },
    {
      "t": "2026-06-25T21:02:29.915001Z",
      "s": 2.0
    },
    {
      "t": "2026-06-26T05:19:45.703917Z",
      "s": 3.0
    },
    {
      "t": "2026-06-26T08:36:57.255686Z",
      "s": 3.5
    },
    {
      "t": "2026-06-26T09:02:41.612913Z",
      "s": 3.4
    },
    {
      "t": "2026-06-26T10:02:46.948975Z",
      "s": 3.0
    },
    {
      "t": "2026-06-26T11:02:47.706181Z",
      "s": 2.8
    },
    {
      "t": "2026-06-26T11:28:20.640723Z",
      "s": 3.0
    },
    {
      "t": "2026-06-26T12:02:48.111654Z",
      "s": 2.9
    },
    {
      "t": "2026-06-26T13:02:56.209899Z",
      "s": 2.8
    },
    {
      "t": "2026-06-26T14:02:50.350976Z",
      "s": 2.7
    },
    {
      "t": "2026-06-26T15:02:47.805974Z",
      "s": 2.6
    },
    {
      "t": "2026-06-26T16:02:45.400407Z",
      "s": 2.5
    },
    {
      "t": "2026-06-26T17:02:52.210147Z",
      "s": 2.4
    },
    {
      "t": "2026-06-26T18:16:30.846246Z",
      "s": 2.3
    }
  ]
}