{
  "updated_at": "2026-06-14T13:01:54.795894Z",
  "ostatnia_ocena": 2.5,
  "ostatnie_powiadomienie_at": null,
  "stan_swiata": [
    {
      "temat": "EU energy prices / Iran deal",
      "poziom_bazowy": 2.2,
      "cykle_bez_zmian": 20,
      "opis": "Iran deal still unconfirmed — continuation; cycle incremented, baseline nudged down slightly."
    },
    {
      "temat": "EU enlargement (Ukraine/Moldova)",
      "poziom_bazowy": 1.0,
      "cykle_bez_zmian": 37,
      "opis": "Accession process ongoing without new development — baseline at floor."
    }
  ]
}