{
  "updated_at": "2026-06-15T04:02:03.482382Z",
  "ostatnia_ocena": 6.0,
  "ostatnie_powiadomienie_at": null,
  "stan_swiata": [
    {
      "temat": "Russia-Ukraine war (active combat)",
      "poziom_bazowy": 6.0,
      "cykle_bez_zmian": 4,
      "opis": "War continues at maximum background level — no decay applied at this extreme; no qualitative change this cycle."
    },
    {
      "temat": "EU accession process",
      "poziom_bazowy": 1.0,
      "cykle_bez_zmian": 17,
      "opis": "EU formally advancing membership talks — minor qualitative continuation."
    },
    {
      "temat": "Western support / US-Iran ceasefire impact",
      "poziom_bazowy": 5.5,
      "cykle_bez_zmian": 0,
      "opis": "US-Iran ceasefire officially announced — qualitative step from 'deal expected' to 'ceasefire confirmed'; concern about US attention diversion from Ukraine increases slightly. Baseline raised."
    }
  ],
  "score_history": [
    {
      "t": "2026-06-14T19:01:54.298596Z",
      "s": 8.4
    },
    {
      "t": "2026-06-14T20:02:04.671653Z",
      "s": 8.1
    },
    {
      "t": "2026-06-14T20:10:06.606178Z",
      "s": 7.8
    },
    {
      "t": "2026-06-14T20:50:53.691292Z",
      "s": 7.5
    },
    {
      "t": "2026-06-14T21:01:52.889753Z",
      "s": 7.2
    },
    {
      "t": "2026-06-14T22:01:58.487045Z",
      "s": 2.5
    },
    {
      "t": "2026-06-14T23:01:56.579793Z",
      "s": 2.5
    },
    {
      "t": "2026-06-15T00:01:53.257808Z",
      "s": 6.0
    },
    {
      "t": "2026-06-15T01:01:58.027689Z",
      "s": 6.9
    },
    {
      "t": "2026-06-15T02:01:48.703008Z",
      "s": 6.6
    },
    {
      "t": "2026-06-15T03:01:58.482932Z",
      "s": 6.3
    },
    {
      "t": "2026-06-15T04:02:03.480459Z",
      "s": 6.0
    }
  ]
}