{
  "updated_at": "2026-06-11T21:02:14.530955Z",
  "ostatnia_ocena": 4.5,
  "ostatnie_powiadomienie_at": null,
  "stan_swiata": [
    {
      "temat": "Konflikt USA-Iran",
      "poziom_bazowy": 5.0,
      "cykle_bez_zmian": 3,
      "opis": "No new military escalation this cycle; decay continues. Background risk persists."
    },
    {
      "temat": "Bezpieczeństwo dyplomatyczne USA / atak na konsulat w Toronto",
      "poziom_bazowy": 3.0,
      "cykle_bez_zmian": 3,
      "opis": "Toronto police officer shot while investigating the consulate attack — minor new development but investigation still ongoing. Slight persistence."
    },
    {
      "temat": "Chiny-Korea Północna / Indo-Pacyfik",
      "poziom_bazowy": 4.5,
      "cykle_bez_zmian": 0,
      "opis": "Xi visit to Pyongyang confirmed and materialised this cycle; qualitative step in axis consolidation — uptick applied."
    },
    {
      "temat": "Dominacja dolara / złoto jako rezerwa",
      "poziom_bazowy": 2.5,
      "cykle_bez_zmian": 3,
      "opis": "Ongoing structural shift in reserve assets; no new developments this cycle. Decay applied."
    }
  ]
}