{
  "updated_at": "2026-06-12T10:01:50.860462Z",
  "ostatnia_ocena": 2.3,
  "ostatnie_powiadomienie_at": null,
  "stan_swiata": [
    {
      "temat": "EU energy prices & cost of living",
      "poziom_bazowy": 2.0,
      "cykle_bez_zmian": 3,
      "opis": "Iran deal stalled; no energy price relief confirmed; continued slow decay."
    },
    {
      "temat": "Wildfire / climate risk in Iberia",
      "poziom_bazowy": 4.0,
      "cykle_bez_zmian": 7,
      "opis": "No new wildfire incident this cycle; seasonal risk remains but baseline continues to decay."
    }
  ]
}