{
  "updated_at": "2026-06-12T19:02:07.863261Z",
  "ostatnia_ocena": 7.5,
  "ostatnie_powiadomienie_at": null,
  "stan_swiata": [
    {
      "temat": "Active war with Russia / air strikes / infrastructure",
      "poziom_bazowy": 7.5,
      "cykle_bez_zmian": 3,
      "opis": "No new major Russian escalation; same qualitative level. Slight decay continues but baseline remains very high."
    },
    {
      "temat": "Western military aid continuity",
      "poziom_bazowy": 4.2,
      "cykle_bez_zmian": 1,
      "opis": "US NATO asset cuts remain a background negative signal; no new direct aid cut announced this cycle. Baseline holds."
    }
  ]
}