{
  "updated_at": "2026-06-14T09:02:05.425990Z",
  "ostatnia_ocena": 4.2,
  "ostatnie_powiadomienie_at": null,
  "stan_swiata": [
    {
      "temat": "Russia-Ukraine war / Black Sea security",
      "poziom_bazowy": 2.5,
      "cykle_bez_zmian": 32,
      "opis": "War continues near Romania's border without new escalation — decay applied, baseline stable."
    },
    {
      "temat": "Moldova and Ukraine EU accession",
      "poziom_bazowy": 1.5,
      "cykle_bez_zmian": 32,
      "opis": "Accession process ongoing without new development — baseline at floor."
    },
    {
      "temat": "Energy prices / Iran deal",
      "poziom_bazowy": 3.0,
      "cykle_bez_zmian": 15,
      "opis": "Iran deal signals slightly more concrete but still unconfirmed — continuation; cycle incremented, baseline nudged down."
    }
  ]
}