{
  "updated_at": "2026-06-14T18:02:06.708727Z",
  "ostatnia_ocena": 9.0,
  "ostatnie_powiadomienie_at": null,
  "stan_swiata": [
    {
      "temat": "Russia-Ukraine war (active combat)",
      "poziom_bazowy": 9.0,
      "cykle_bez_zmian": 43,
      "opis": "War continues at maximum background level — no decay applied at this extreme."
    },
    {
      "temat": "EU accession process",
      "poziom_bazowy": 2.0,
      "cykle_bez_zmian": 4,
      "opis": "EU formally advancing membership talks — minor qualitative continuation; cycle incremented."
    },
    {
      "temat": "Western support / US focus on Iran deal",
      "poziom_bazowy": 5.0,
      "cykle_bez_zmian": 5,
      "opis": "Iran deal still unresolved; Beirut strikes complicate US Middle East focus — continuation; cycle incremented, baseline nudged down slightly."
    }
  ]
}